{"cameraMode":{"drawMode":0,"name":"Shaded","section":"Shading Mode"},"sceneLighting":true,"audioPlay":false,"sceneViewState":{"showFog":true,"showMaterialUpdate":false,"showSkybox":true,"showFlares":true,"showImageEffects":true,"showParticleSystems":true},"in2DMode":false,"pivot":{"x":0.08766929060220719,"y":1.1027554273605347,"z":3.8472671508789064},"rotation":{"x":-0.5977199673652649,"y":-0.07553839683532715,"z":0.05671412870287895,"w":-0.796120822429657},"size":17.458820343017579,"orthographic":false}